{
  "customers": [
    {
      "firstName": "zibaaaa",
      "lastName": "shahabi",
      "idNumber": "123456789",
      "birthDayDate": "03/03/2001",
      "phoneNumber": "09395789412",
      "status": 3,
      "email": "nooshin@gmail.com",
      "id": "68e00db922f48455465040c2"
    },
    {
      "firstName": "sanazi",
      "lastName": "abaspour",
      "idNumber": "123456789",
      "birthDayDate": "01/02/2001",
      "phoneNumber": "09368794520",
      "email": "elehe@gmail.com",
      "id": "1a2e"
    },
    {
      "firstName": "sanaz",
      "lastName": "nimati",
      "idNumber": "852369741",
      "birthDayDate": "01/04/2019",
      "phoneNumber": "0936852147",
      "email": "sahar@gmail.com",
      "id": "da61"
    },
    {
      "id": "ab1a",
      "firstName": "mohammad",
      "lastName": "khaleghi",
      "idNumber": "123456789",
      "birthDayDate": "17/03/2005",
      "phoneNumber": "09356892478",
      "status": 2,
      "email": "mohammad@gmail.com"
    },
    {
      "id": "e7d2",
      "firstName": "maryam",
      "lastName": "elahi",
      "idNumber": "123456789",
      "birthDayDate": "07/08/1993",
      "phoneNumber": "45896325",
      "status": 3,
      "email": "maryam@yahoo.com"
    },
    {
      "firstName": "mojtaba",
      "lastName": "atashi",
      "idNumber": "2558947132",
      "birthDayDate": "31/07/1997",
      "phoneNumber": "09387942563",
      "email": "majid@gmail.com",
      "id": "8fcb"
    },
    {
      "firstName": "ali",
      "lastName": "alavi",
      "idNumber": "1234563",
      "birthDayDate": "31/11/2005",
      "phoneNumber": "215662236",
      "email": "ali@gmail.com",
      "id": "7c9c"
    }
  ]
}